kicomav/__init__.py
kicomav/k2.py
kicomav/kavcore/__init__.py
kicomav/kavcore/config.py
kicomav/kavcore/k2const.py
kicomav/kavcore/k2engine.py
kicomav/kavcore/k2file.py
kicomav/kavcore/k2security.py
kicomav/kavcore/k2timelib.py
kicomav/kavcore/plugin_base.py
kicomav/kavcore/scanner.py
kicomav/kavcore/updater.py
kicomav/plugins/__init__.py
kicomav/plugins/adware.py
kicomav/plugins/alz.py
kicomav/plugins/attach.py
kicomav/plugins/bz.py
kicomav/plugins/cab.py
kicomav/plugins/carch.py
kicomav/plugins/cryptolib.py
kicomav/plugins/dde.py
kicomav/plugins/dummy.py
kicomav/plugins/egg.py
kicomav/plugins/eicar.py
kicomav/plugins/elf.py
kicomav/plugins/emalware.py
kicomav/plugins/eml.py
kicomav/plugins/eps.py
kicomav/plugins/gz.py
kicomav/plugins/html.py
kicomav/plugins/hwp.py
kicomav/plugins/hwpx.py
kicomav/plugins/icon.py
kicomav/plugins/ishield.py
kicomav/plugins/iso.py
kicomav/plugins/kavutil.py
kicomav/plugins/kernel.py
kicomav/plugins/kicom.lst
kicomav/plugins/lnk.py
kicomav/plugins/macro.py
kicomav/plugins/nsis.py
kicomav/plugins/ole.py
kicomav/plugins/olenative.py
kicomav/plugins/pdf.py
kicomav/plugins/pe.py
kicomav/plugins/pyz.py
kicomav/plugins/rar.py
kicomav/plugins/rtf.py
kicomav/plugins/script.py
kicomav/plugins/tar.py
kicomav/plugins/tnef.py
kicomav/plugins/unpack.py
kicomav/plugins/upx.py
kicomav/plugins/ve.py
kicomav/plugins/vhd.py
kicomav/plugins/xz.py
kicomav/plugins/yaraex.py
kicomav/plugins/zip.py
kicomav-0.40.dist-info/licenses/LICENSE
kicomav-0.40.dist-info/METADATA
kicomav-0.40.dist-info/WHEEL
kicomav-0.40.dist-info/entry_points.txt
kicomav-0.40.dist-info/top_level.txt
kicomav-0.40.dist-info/RECORD
