Metadata-Version: 2.4
Name: kicomav
Version: 0.40
Summary: KICOM Anti-Virus II - Open source antivirus engine for Python
Author-email: Kei Choi <hanul93@gmail.com>
License: MIT
Project-URL: Homepage, https://github.com/hanul93/kicomav
Project-URL: Repository, https://github.com/hanul93/kicomav
Project-URL: Documentation, https://github.com/hanul93/kicomav#readme
Project-URL: Bug Tracker, https://github.com/hanul93/kicomav/issues
Keywords: antivirus,malware,security,scanner,virus
Classifier: Development Status :: 4 - Beta
Classifier: Environment :: Console
Classifier: Intended Audience :: Developers
Classifier: Intended Audience :: Information Technology
Classifier: License :: OSI Approved :: MIT License
Classifier: Operating System :: OS Independent
Classifier: Programming Language :: Python :: 3
Classifier: Programming Language :: Python :: 3.10
Classifier: Programming Language :: Python :: 3.11
Classifier: Programming Language :: Python :: 3.12
Classifier: Programming Language :: Python :: 3.13
Classifier: Topic :: Security
Classifier: Topic :: System :: Systems Administration
Requires-Python: >=3.10
License-File: LICENSE
Requires-Dist: rich>=13.0.0
Requires-Dist: requests>=2.28.0
Requires-Dist: python-dotenv>=1.0.0
Requires-Dist: yara-python>=4.3.0
Requires-Dist: py7zr>=0.20.0
Requires-Dist: rarfile>=4.0
Requires-Dist: pycabfile>=0.1.0
Provides-Extra: full
Requires-Dist: pylzma>=0.5.0; extra == "full"
Provides-Extra: dev
Requires-Dist: pytest>=7.0.0; extra == "dev"
Requires-Dist: pytest-cov>=4.0.0; extra == "dev"
Requires-Dist: black>=23.0.0; extra == "dev"
Requires-Dist: coverage>=7.0.0; extra == "dev"
Dynamic: license-file
